cenclave_lib_sgx/__init__.py
cenclave_lib_sgx/base64url.py
cenclave_lib_sgx/certificate.py
cenclave_lib_sgx/cli.py
cenclave_lib_sgx/copy.py
cenclave_lib_sgx/error.py
cenclave_lib_sgx/globs.py
cenclave_lib_sgx/http_server.py
cenclave_lib_sgx/py.typed
cenclave_lib_sgx/sgx/__init__.py
cenclave_lib_sgx/sgx/key.py
cenclave_lib_sgx/sgx/quote.py
cenclave_lib_sgx-1.1.1.dist-info/METADATA
cenclave_lib_sgx-1.1.1.dist-info/WHEEL
cenclave_lib_sgx-1.1.1.dist-info/entry_points.txt
cenclave_lib_sgx-1.1.1.dist-info/top_level.txt
cenclave_lib_sgx-1.1.1.dist-info/RECORD
