Metadata-Version: 2.1
Name: cenclave-lib-sgx
Version: 1.1.1
Summary: Library to bootstrap WSGI/ASGI application for Gramine
Author-email: Cosmian Tech <tech@cosmian.com>
License: MIT
Classifier: Development Status :: 6 - Mature
Classifier: License :: OSI Approved :: MIT License
Classifier: Operating System :: POSIX :: Linux
Classifier: Programming Language :: Python :: 3
Classifier: Programming Language :: Python :: Implementation :: CPython
Requires-Python: >=3.10
Requires-Dist: cryptography<44.0.0,>=43.0.3
Requires-Dist: intel-sgx-ra<2.4.0,>=2.3.1
Requires-Dist: hypercorn[uvloop]<0.18.0,>=0.17.3
Requires-Dist: h2<4.2.0,>=4.1.0
Requires-Dist: uvicorn[standard]<1.0.0,>=0.34.0
Requires-Dist: cenclave-lib-crypto<1.1.0,>=1.0.0
Provides-Extra: dev
Requires-Dist: black<25.0.0,>=24.10.0; extra == "dev"
Requires-Dist: isort<6.0.0,>=5.13.2; extra == "dev"
Requires-Dist: pylint<4.0.0,>=3.3.1; extra == "dev"
Requires-Dist: pycodestyle<3.0.0,>=2.12.1; extra == "dev"
Requires-Dist: pydocstyle<7.0.0,>=6.3.0; extra == "dev"
Requires-Dist: mypy<2.0.0,>=1.13.0; extra == "dev"
Requires-Dist: pytest<9.0.0,>=8.3.3; extra == "dev"
Requires-Dist: build<1.3.0,>=1.2.2; extra == "dev"
Requires-Dist: wheel<0.50.0,>=0.45.0; extra == "dev"
